<?xml version="1.0" encoding="utf-8" ?><dwsync><file name="Channel1.txt" server="192.186.199.4/public_html/" local="3473828640" remote="20653697824" /><file name="Channel10.txt" server="192.186.199.4/public_html/" local="3473828640" remote="20653697824" /><file name="Channel11.txt" server="192.186.199.4/public_html/" local="3473828640" remote="20653697824" /><file name="Channel12.txt" server="192.186.199.4/public_html/" local="3473828640" remote="20653697824" /><file name="Channel13.txt" server="192.186.199.4/public_html/" local="3473828640" remote="20653697824" /><file name="Channel14.txt" server="192.186.199.4/public_html/" local="3473828640" remote="20653697824" /><file name="Channel15.txt" server="192.186.199.4/public_html/" local="3473828640" remote="20653697824" /><file name="Channel16.txt" server="192.186.199.4/public_html/" local="3473828640" remote="20653697824" /></dwsync>